gridgraphs/__init__.py
gridgraphs/directions.py
gridgraphs/grid_graph.py
gridgraphs/islands.py
gridgraphs/main.py
gridgraphs/strategies.py
gridgraphs/version.py
gridgraphs-0.1.0.dist-info/LICENSE
gridgraphs-0.1.0.dist-info/WHEEL
gridgraphs-0.1.0.dist-info/METADATA
gridgraphs-0.1.0.dist-info/RECORD
