Metadata-Version: 2.1
Name: gridgraphs
Version: 0.1.0
Summary: Grid graphs and island solutions in 2D and 3D, object-oriented and pure python/numpy.
Author-email: Emir Karamehmetoglu <emirkmo@github.com>
Requires-Python: >=3.10
Classifier: License :: OSI Approved :: GNU General Public License v3 or later (GPLv3+)
Requires-Dist: numpy>=1.20
Project-URL: Home, https://github.com/emirkmo/Grid-graphs-with-python
